{
  "id": "ea5039e3-8fe6-4271-8689-91bff16e76f8",
  "slug": "northern-light-aviation",
  "name": "Northern Light Aviation",
  "continent": "Europe",
  "country": "United Kingdom",
  "state": "",
  "city": "",
  "baseAirport": "Derry Airport",
  "website": "https://northernlightaviation.co.uk/",
  "email": "no email",
  "phone": "'+44 7821 319 663",
  "about": "Northern Light Aviation is a reputable flight training institution based in the UK, offering comprehensive aviation education with CAA-approved instructors. Our programs are designed to help students work towards gaining various aviation certifications. With a focus on safety, professionalism, and personalized instruction, we provide a supportive environment for aspiring pilots to develop their skills. Our experienced instructors guide students through rigorous training, ensuring they are well-prepared for a successful career in aviation. At Northern Light Aviation, we believe that your wings already exist, and we are here to help you take flight.",
  "icao": "",
  "iata": "",
  "rating": null,
  "ratingsNumber": null,
  "services": "[\"Private Pilot License\"]",
  "visaInsurance": "",
  "fleetSize": "",
  "logoUrl": ""
}