{
  "id": "24338024-652a-4532-8fb4-4f39f63880a7",
  "slug": "revv-aviation",
  "name": "Revv Aviation",
  "continent": "North America",
  "country": "United States",
  "state": "IA",
  "city": "",
  "baseAirport": "DVN -Davenport Municipal Airport",
  "website": "https://revvaviation.com/locations/davenport-ia/",
  "email": "DVNfrontdesk@revvaviation.com",
  "phone": "(563) 391-5650",
  "about": "Revv Aviation is a pioneering flight school and aviation services provider dedicated to bringing personal aviation to smaller towns across the Midwest. Founded in 2022, Revv is driven by a passion for aviation and a commitment to making flying accessible and affordable. With multiple locations, including Omaha, Nebraska, and Sioux City, Iowa, Revv offers comprehensive flight training from private pilot to airline transport pilot levels, all meeting FAA requirements. Our experienced instructors and advanced aeronautical technology ensure safe and proficient pilots. Revv also provides air charter services, aircraft rental, and other aviation needs, fostering a community of aviators and promoting the joy and wonder of flying for everyone. Our mission is to introduce personal aviation to more people, ensuring excellence in every aspect of our services.",
  "icao": "",
  "iata": "",
  "rating": null,
  "ratingsNumber": null,
  "services": "[\"Computerized Testing\\nExaminer\\nGround School\\nSimulator\\nAirline Transport Pilot ATP\\nCommercial\\nFlight Instructor CFI\\nFlight Instructor Instrument CFII\\nMulti Engine Instructor MEI\\nPrivate Pilot\\nRecreational Pilot\\nInstrument\\nMulti-Engine\"]",
  "visaInsurance": "",
  "fleetSize": "",
  "logoUrl": ""
}