{
  "id": "87a8942c-0f9b-4703-99f9-fead61b3e975",
  "slug": "skyhawk-aviation-pty-ltd-rustenburg",
  "name": "Skyhawk Aviation (Pty) Ltd - Rustenburg",
  "continent": "Africa",
  "country": "South Africa",
  "state": "NW",
  "city": "",
  "baseAirport": "Lanseria International Airport",
  "website": "https://skyhawk.co.za/",
  "email": "info@skyhawk.co.za",
  "phone": "011 659 1004",
  "about": "Skyhawk Aviation (Pty) Ltd, based at Lanseria International Airport but with operations at Rustenburg Airfield, is a comprehensive flight training institution dedicated to providing the highest standard of pilot training. Established to fill the niche for high-quality, personalized instruction, Skyhawk avoids the \"sausage machine\" approach, ensuring students benefit from experienced instructors. The school offers a wide range of courses, including Private Pilot License, Night Rating, Commercial Pilot License, ATPL Preparation, Instrument Rating, and Flight Instructor ratings. Training is conducted on traditional flight instrument-equipped Cessna 172 and Piper Seneca aircraft, preparing students for the realities of commercial aviation. Skyhawk's Career Pilot Program allows aspirants to progress through a structured career path, including working as flight instructors. The school is committed to setting students on a solid foundation for their future careers in aviation.",
  "icao": "",
  "iata": "",
  "rating": null,
  "ratingsNumber": null,
  "services": "[\"ATPL (Modular - A)\\nClass Rating\\nCPL - (Modular - H)\\nFlight Instructor\\nNight Rating\"]",
  "visaInsurance": "",
  "fleetSize": "",
  "logoUrl": ""
}